SimilarNeuron/__init__.py
SimilarNeuron/exception.py
SimilarNeuron/typing.py
SimilarNeuron/FuncAdapter/__init__.py
SimilarNeuron/FuncAdapter/funcAdapter.py
SimilarNeuron/Granular/__init__.py
SimilarNeuron/Granular/condition.py
SimilarNeuron/Granular/constraint.py
SimilarNeuron/Granular/granular.py
SimilarNeuron/Listener/__init__.py
SimilarNeuron/Listener/listener.py
SimilarNeuron/utils/__init__.py
SimilarNeuron/utils/agreement.py
SimilarNeuron/utils/container.py
SimilarNeuron/utils/dicttool.py
SimilarNeuron-0.0.3.dist-info/LICENSE
SimilarNeuron-0.0.3.dist-info/METADATA
SimilarNeuron-0.0.3.dist-info/WHEEL
SimilarNeuron-0.0.3.dist-info/top_level.txt
SimilarNeuron-0.0.3.dist-info/RECORD
